luxuryvtontest/__init__.py
luxuryvtontest/test.py
luxuryvtontest/folder_test/__init__.py
luxuryvtontest/folder_test/f_test.py
luxuryvtontest/folder_test/test2/__init__.py
luxuryvtontest/folder_test/test2/test_import.py
luxuryvtontest-0.0.18.dist-info/METADATA
luxuryvtontest-0.0.18.dist-info/WHEEL
luxuryvtontest-0.0.18.dist-info/top_level.txt
luxuryvtontest-0.0.18.dist-info/RECORD
