Metadata-Version: 2.1
Name: luxuryvtontest
Version: 0.0.18
Summary: This is a test for my python package upload to pypi
Home-page: https://github.com/powerjsv/jsv_package_test
Author: powerjsv
Author-email: powerjsv12@gmail.com
Keywords: vton,powerjsv,toy project,pypi
Classifier: Programming Language :: Python :: 3.10
Classifier: Programming Language :: Python :: 3.11
Requires-Python: >=3.10
